api_insights_sdk/__init__.py
api_insights_sdk/django_middleware.py
api_insights_sdk/flask_extension.py
api_insights_sdk/tracker.py
api_insights_sdk-1.0.0.dist-info/licenses/LICENSE
api_insights_sdk-1.0.0.dist-info/METADATA
api_insights_sdk-1.0.0.dist-info/WHEEL
api_insights_sdk-1.0.0.dist-info/top_level.txt
api_insights_sdk-1.0.0.dist-info/RECORD
