Metadata-Version: 2.4
Name: api-insights-sdk
Version: 1.0.0
Summary: SDK for tracking API requests
Author-email: API Insights <rahulrathod315@gmail.com>
License: MIT
Requires-Python: >=3.8
License-File: LICENSE
Dynamic: license-file
